zhinst/qcodes/__init__.py
zhinst/qcodes/_version.py
zhinst/qcodes/device_creator.py
zhinst/qcodes/py.typed
zhinst/qcodes/qcodes_adaptions.py
zhinst/qcodes/session.py
zhinst/qcodes/driver/__init__.py
zhinst/qcodes/driver/devices/__init__.py
zhinst/qcodes/driver/devices/base.py
zhinst/qcodes/driver/devices/hdawg.py
zhinst/qcodes/driver/devices/pqsc.py
zhinst/qcodes/driver/devices/shfqa.py
zhinst/qcodes/driver/devices/shfqc.py
zhinst/qcodes/driver/devices/shfsg.py
zhinst/qcodes/driver/devices/uhfli.py
zhinst/qcodes/driver/devices/uhfqa.py
zhinst/qcodes/driver/modules/__init__.py
zhinst/qcodes/driver/modules/base_module.py
zhinst/qcodes/driver/modules/daq_module.py
zhinst/qcodes/driver/modules/device_settings_module.py
zhinst/qcodes/driver/modules/impedance_module.py
zhinst/qcodes/driver/modules/pid_advisor_module.py
zhinst/qcodes/driver/modules/precompensation_advisor_module.py
zhinst/qcodes/driver/modules/scope_module.py
zhinst/qcodes/driver/modules/shfqa_sweeper.py
zhinst/qcodes/driver/modules/sweeper_module.py
zhinst_qcodes-0.6.0.dist-info/AUTHORS
zhinst_qcodes-0.6.0.dist-info/LICENSE
zhinst_qcodes-0.6.0.dist-info/METADATA
zhinst_qcodes-0.6.0.dist-info/WHEEL
zhinst_qcodes-0.6.0.dist-info/top_level.txt
zhinst_qcodes-0.6.0.dist-info/RECORD
