Metadata-Version: 2.1
Name: zhinst-qcodes
Version: 0.6.0
Summary: Zurich Instruments drivers for QCoDeS
Home-page: https://github.com/zhinst/zhinst-qcodes
Author: Zurich Instrument
Author-email: info@zhinst.com
Project-URL: Bug Tracker, https://github.com/zhinst/zhinst-qcodes/issues
Project-URL: Documentation, https://docs.zhinst.com/zhinst-qcodes/en/latest/
Project-URL: Release notes, https://docs.zhinst.com/zhinst-qcodes/en/latest/changelog/index.html
Project-URL: Source, https://github.com/zhinst/zhinst-qcodes
Classifier: Development Status :: 4 - Beta
Classifier: Programming Language :: Python :: 3.10
Classifier: Programming Language :: Python :: 3.11
Classifier: Programming Language :: Python :: 3.12
Classifier: License :: OSI Approved :: MIT License
Classifier: Operating System :: OS Independent
Classifier: Topic :: Scientific/Engineering
Classifier: Intended Audience :: Science/Research
Requires-Python: >=3.10
License-File: LICENSE
License-File: AUTHORS
Requires-Dist: numpy>=1.13
Requires-Dist: zhinst-toolkit>=0.7.0
Requires-Dist: qcodes>=0.30.0
Requires-Dist: typing_extensions>=4.1.1
